apricopt/__init__.py
apricopt/IO/__init__.py
apricopt/IO/data_input.py
apricopt/model/FastObservable.py
apricopt/model/LogObservable.py
apricopt/model/Model.py
apricopt/model/ModelInstance.py
apricopt/model/Observable.py
apricopt/model/ObservableFunction.py
apricopt/model/ObservableFunctionNotFoundError.py
apricopt/model/Parameter.py
apricopt/model/__init__.py
apricopt/sampling/Sampler.py
apricopt/sampling/__init__.py
apricopt/simulation/SimulationEngine.py
apricopt/simulation/__init__.py
apricopt/simulation/COPASI/COPASIEngine.py
apricopt/simulation/COPASI/COPASIModelInstance.py
apricopt/simulation/COPASI/__init__.py
apricopt/simulation/MockUp/MockUpModelInstance.py
apricopt/simulation/MockUp/MockUpSimulationEngine.py
apricopt/simulation/MockUp/__init__.py
apricopt/simulation/executable/ExecutableEngine.py
apricopt/simulation/executable/ExecutableModelInstance.py
apricopt/simulation/executable/__init__.py
apricopt/simulation/executable/Modelica/ModelicaExecutableEngine.py
apricopt/simulation/executable/Modelica/ModelicaExecutableEngineWithFiles.py
apricopt/simulation/executable/Modelica/__init__.py
apricopt/simulation/roadrunner/RoadRunnerEngine.py
apricopt/simulation/roadrunner/RoadRunnerModelInstance.py
apricopt/simulation/roadrunner/__init__.py
apricopt/solving/__init__.py
apricopt/solving/blackbox/BlackBox.py
apricopt/solving/blackbox/BlackBoxSolver.py
apricopt/solving/blackbox/FunctionBlackBox.py
apricopt/solving/blackbox/SimulableModelBlackBox.py
apricopt/solving/blackbox/__init__.py
apricopt/solving/blackbox/MockUp/MockUpSolver.py
apricopt/solving/blackbox/MockUp/__init__.py
apricopt/solving/blackbox/NOMAD/NOMADSolver.py
apricopt/solving/blackbox/NOMAD/__init__.py
apricopt/solving/blackbox/pyswarms/PySwarmsSolver.py
apricopt/solving/blackbox/pyswarms/__init__.py
apricopt/solving/blackbox/scipy/SciPySolver.py
apricopt/solving/blackbox/scipy/__init__.py
apricopt/solving/whitebox/WhiteBoxSolver.py
apricopt/solving/whitebox/__init__.py
apricopt-0.0.2a3.dev19.dist-info/COPYING
apricopt-0.0.2a3.dev19.dist-info/METADATA
apricopt-0.0.2a3.dev19.dist-info/WHEEL
apricopt-0.0.2a3.dev19.dist-info/top_level.txt
apricopt-0.0.2a3.dev19.dist-info/RECORD
