Metadata-Version: 2.1
Name: apricopt
Version: 0.0.2a3.dev19
Summary: A library for simulation-based parameter optimization
Home-page: http://mclab.di.uniroma1.it
Author: Marco Esposito
Author-email: esposito@di.uniroma1.it
Classifier: Programming Language :: Python :: 3
Classifier: License :: OSI Approved :: GNU General Public License v3 (GPLv3)
Classifier: Operating System :: OS Independent
Requires-Python: >=3.6
License-File: COPYING
Requires-Dist: attrs (==21.2.0)
Requires-Dist: chaospy (==4.3.9)
Requires-Dist: cycler (==0.10.0)
Requires-Dist: future (==0.18.2)
Requires-Dist: importlib-metadata (==3.1.0)
Requires-Dist: kiwisolver (==1.3.2)
Requires-Dist: matplotlib (==3.5.0)
Requires-Dist: mpmath (==1.2.1)
Requires-Dist: numpy (==1.24.1)
Requires-Dist: Pillow (==8.3.2)
Requires-Dist: pyparsing (==2.4.7)
Requires-Dist: python-dateutil (==2.8.2)
Requires-Dist: python-libsbml (==5.19.5)
Requires-Dist: PyYAML (==5.4.1)
Requires-Dist: scipy (==1.8.1)
Requires-Dist: seaborn (==0.11.0)
Requires-Dist: six (==1.16.0)
Requires-Dist: sympy (==1.11.1)
Requires-Dist: tqdm (==4.62.2)
Requires-Dist: zipp (==3.4.0)
